{
  "7day": {
    "articleCount": 15,
    "sentimentBreakdown": {
      "bullish": 11,
      "bearish": 3,
      "neutral": 1
    },
    "topTopics": [
      {
        "topic": "Lagos real estate",
        "count": 3
      },
      {
        "topic": "housing deficit",
        "count": 2
      },
      {
        "topic": "affordable housing",
        "count": 2
      },
      {
        "topic": "facilities management",
        "count": 1
      },
      {
        "topic": "property value enhancement",
        "count": 1
      }
    ],
    "averageSentiment": "bullish"
  },
  "30day": {
    "articleCount": 15,
    "sentimentBreakdown": {
      "bullish": 11,
      "bearish": 3,
      "neutral": 1
    },
    "topTopics": [
      {
        "topic": "Lagos real estate",
        "count": 3
      },
      {
        "topic": "housing deficit",
        "count": 2
      },
      {
        "topic": "affordable housing",
        "count": 2
      },
      {
        "topic": "facilities management",
        "count": 1
      },
      {
        "topic": "property value enhancement",
        "count": 1
      }
    ],
    "averageSentiment": "bullish"
  },
  "90day": {
    "articleCount": 15,
    "sentimentBreakdown": {
      "bullish": 11,
      "bearish": 3,
      "neutral": 1
    },
    "topTopics": [
      {
        "topic": "Lagos real estate",
        "count": 3
      },
      {
        "topic": "housing deficit",
        "count": 2
      },
      {
        "topic": "affordable housing",
        "count": 2
      },
      {
        "topic": "facilities management",
        "count": 1
      },
      {
        "topic": "property value enhancement",
        "count": 1
      }
    ],
    "averageSentiment": "bullish"
  }
}