{
  "7day": {
    "articleCount": 2,
    "sentimentBreakdown": {
      "neutral": 1,
      "bullish": 1
    },
    "topTopics": [
      {
        "topic": "Abuja real estate",
        "count": 1
      },
      {
        "topic": "quality and innovation",
        "count": 1
      },
      {
        "topic": "Nigeria property market",
        "count": 1
      },
      {
        "topic": "agriculture",
        "count": 1
      },
      {
        "topic": "land ownership",
        "count": 1
      }
    ],
    "averageSentiment": "neutral"
  },
  "30day": {
    "articleCount": 2,
    "sentimentBreakdown": {
      "neutral": 1,
      "bullish": 1
    },
    "topTopics": [
      {
        "topic": "Abuja real estate",
        "count": 1
      },
      {
        "topic": "quality and innovation",
        "count": 1
      },
      {
        "topic": "Nigeria property market",
        "count": 1
      },
      {
        "topic": "agriculture",
        "count": 1
      },
      {
        "topic": "land ownership",
        "count": 1
      }
    ],
    "averageSentiment": "neutral"
  },
  "90day": {
    "articleCount": 2,
    "sentimentBreakdown": {
      "neutral": 1,
      "bullish": 1
    },
    "topTopics": [
      {
        "topic": "Abuja real estate",
        "count": 1
      },
      {
        "topic": "quality and innovation",
        "count": 1
      },
      {
        "topic": "Nigeria property market",
        "count": 1
      },
      {
        "topic": "agriculture",
        "count": 1
      },
      {
        "topic": "land ownership",
        "count": 1
      }
    ],
    "averageSentiment": "neutral"
  }
}